{
    "msg": "",
    "code": 0,
    "data": {
        "disps": [
            {
                "displayId": "2008001",
                "displayName": "开奖号码",
                "displayCode": "kjhm",
                "defaultItem": 1,
                "lotteryId": "15"
            },
            {
                "displayId": "10080012",
                "displayName": "基本走势 ",
                "displayCode": "jbzs",
                "defaultItem": 1,
                "lotteryId": "15"
            }
        ]
    }
}
